README.md
setup.cfg
setup.py
hspectral/__init__.py
hspectral/_version.py
hspectral.egg-info/PKG-INFO
hspectral.egg-info/SOURCES.txt
hspectral.egg-info/dependency_links.txt
hspectral.egg-info/not-zip-safe
hspectral.egg-info/requires.txt
hspectral.egg-info/top_level.txt
hspectral/detectors/RX.py
hspectral/detectors/__init__.py
hspectral/generators/__init__.py
hspectral/generators/generators.py
hspectral/tests/__init__.py
hspectral/tests/test_detectors.py
hspectral/tests/test_generators.py
hspectral/utils/__init__.py
hspectral/utils/basic.py