Metadata-Version: 1.2
Name: hspectral
Version: 0.1
Summary: Toolbox for hyperspectral data.
Home-page: https://github.com/w4k2/stream-learn
Maintainer: P. Ksieniewicz
Maintainer-email: pawel.ksieniewicz@pwr.edu.pl
License: MIT
Download-URL: https://github.com/w4k2/stream-learn
Platform: UNKNOWN
Classifier: Intended Audience :: Science/Research
Classifier: Programming Language :: Python
Classifier: Topic :: Scientific/Engineering
Classifier: Operating System :: POSIX
Classifier: Operating System :: Unix
Classifier: Operating System :: MacOS
Classifier: Programming Language :: Python :: 2.7
